base64_bytesio/__init__.py
base64_bytesio/base64_bytesio.py
base64_bytesio-0.0.2.dist-info/METADATA
base64_bytesio-0.0.2.dist-info/WHEEL
base64_bytesio-0.0.2.dist-info/licenses/LICENSE
base64_bytesio-0.0.2.dist-info/RECORD
