Metadata-Version: 2.4
Name: base64_bytesio
Version: 0.0.2
Summary: Input a base64 string and return BytesIO
Project-URL: Homepage, https://github.com/BryanJiang-NCI/base64-bytesio
Project-URL: Issues, https://github.com/BryanJiang-NCI/base64-bytesio/issues
Author-email: Bryan Jiang <x23399937@student.ncirl.ie>
License-Expression: MIT
License-File: LICENSE
Classifier: Operating System :: OS Independent
Classifier: Programming Language :: Python :: 3
Requires-Python: >=3.8
